gapfill/__init__.py
gapfill/gapfill.py
gapfill-0.0.7.dist-info/LICENSE
gapfill-0.0.7.dist-info/METADATA
gapfill-0.0.7.dist-info/WHEEL
gapfill-0.0.7.dist-info/top_level.txt
gapfill-0.0.7.dist-info/RECORD
