Metadata-Version: 2.1
Name: gapfill
Version: 0.0.7
Summary: GapFill: A Python module of gap filling functions for motion capture marker data
Home-page: https://github.com/mkjung99/gapfill
Author: Moon Ki Jung
Author-email: m.k.jung@outlook.com
License: UNKNOWN
Platform: UNKNOWN
Classifier: Programming Language :: Python :: 3
Classifier: License :: OSI Approved :: MIT License
Classifier: Operating System :: OS Independent
Requires-Python: >=3.7
